asyncio_pipe/__init__.py
asyncio_pipe-0.0.3.dist-info/METADATA
asyncio_pipe-0.0.3.dist-info/WHEEL
asyncio_pipe-0.0.3.dist-info/top_level.txt
asyncio_pipe-0.0.3.dist-info/RECORD
