Metadata-Version: 2.1
Name: asyncio-pipe
Version: 0.0.3
Summary: Non-blocking IPC with Asyncio
Home-page: https://github.com/rogerthat94/asyncio-pipe
Author: Roger Iyengar
Author-email: ri@rogeriyengar.com
License: UNKNOWN
Platform: UNKNOWN
Classifier: License :: OSI Approved :: Python Software Foundation License
Requires-Python: >=3.6
